bhagavad_gita_api/__init__.py
bhagavad_gita_api/api/__init__.py
bhagavad_gita_api/api/api_v2/__init__.py
bhagavad_gita_api/api/api_v2/api.py
bhagavad_gita_api/api/api_v2/endpoints/__init__.py
bhagavad_gita_api/api/api_v2/endpoints/gita.py
bhagavad_gita_api/api/deps.py
bhagavad_gita_api/cli.py
bhagavad_gita_api/config.py
bhagavad_gita_api/crud.py
bhagavad_gita_api/data/__init__.py
bhagavad_gita_api/data/helpers.py
bhagavad_gita_api/data/insert/__init__.py
bhagavad_gita_api/data/insert/authors.py
bhagavad_gita_api/data/insert/chapters.py
bhagavad_gita_api/data/insert/commentaries.py
bhagavad_gita_api/data/insert/languages.py
bhagavad_gita_api/data/insert/translations.py
bhagavad_gita_api/data/insert/verses.py
bhagavad_gita_api/db/__init__.py
bhagavad_gita_api/db/base_class.py
bhagavad_gita_api/db/init_db.py
bhagavad_gita_api/db/session.py
bhagavad_gita_api/graphql.py
bhagavad_gita_api/gunicorn.conf.py
bhagavad_gita_api/main.py
bhagavad_gita_api/models/__init__.py
bhagavad_gita_api/models/gita.py
bhagavad_gita_api/models/schemas.py
bhagavad_gita_api/models/user.py
bhagavad_gita_api/utils.py
bhagavad_gita_api-2.0.2.dist-info/entry_points.txt
bhagavad_gita_api-2.0.2.dist-info/LICENSE
bhagavad_gita_api-2.0.2.dist-info/WHEEL
bhagavad_gita_api-2.0.2.dist-info/METADATA
bhagavad_gita_api-2.0.2.dist-info/RECORD
